CHANGELOG.rst
MANIFEST.in
README.rst
VERSION
setup.py
guillotina_stripe/__init__.py
guillotina_stripe/behavior.py
guillotina_stripe/cards.py
guillotina_stripe/events.py
guillotina_stripe/install.py
guillotina_stripe/interfaces.py
guillotina_stripe/models.py
guillotina_stripe/product.py
guillotina_stripe/subscription.py
guillotina_stripe/test_package.py
guillotina_stripe/util.py
guillotina_stripe/utility.py
guillotina_stripe/webhook.py
guillotina_stripe.egg-info/PKG-INFO
guillotina_stripe.egg-info/SOURCES.txt
guillotina_stripe.egg-info/dependency_links.txt
guillotina_stripe.egg-info/entry_points.txt
guillotina_stripe.egg-info/requires.txt
guillotina_stripe.egg-info/top_level.txt
guillotina_stripe.egg-info/zip-safe
guillotina_stripe/tests/__init__.py
guillotina_stripe/tests/conftest.py
guillotina_stripe/tests/fixtures.py
guillotina_stripe/tests/payloads.py
guillotina_stripe/tests/test_cards.py
guillotina_stripe/tests/test_charge.py
guillotina_stripe/tests/test_subscription.py