Metadata-Version: 2.1
Name: guillotina-stripe
Version: 1.0.0a12
Summary: guillotina stripe support
Home-page: https://pypi.python.org/pypi/guillotina_stripe
Author: Ramon Navarro Bosch
Author-email: ramon@plone.org
License: GPL version 3
Keywords: guillotina stripe ldap
Platform: UNKNOWN
Classifier: Programming Language :: Python :: 3.7
Classifier: Topic :: Software Development :: Libraries :: Python Modules
Provides-Extra: test
